convcolors/__init__.py
convcolors-2.2.0.dist-info/LICENSE
convcolors-2.2.0.dist-info/METADATA
convcolors-2.2.0.dist-info/WHEEL
convcolors-2.2.0.dist-info/top_level.txt
convcolors-2.2.0.dist-info/RECORD
